yanat/__init__.py
yanat/core.py
yanat/utils.py
yanat-0.1.0.dist-info/METADATA
yanat-0.1.0.dist-info/WHEEL
yanat-0.1.0.dist-info/licenses/LICENSE
yanat-0.1.0.dist-info/RECORD
