Metadata-Version: 2.4
Name: yanat
Version: 0.1.0
Summary: Yet Another Network Analysis Toolbox
Author: Kayson Fakhar, Shrey Dixit
License: MIT
License-File: LICENSE
Classifier: Development Status :: 3 - Alpha
Classifier: Intended Audience :: Science/Research
Classifier: License :: OSI Approved :: MIT License
Classifier: Programming Language :: Python :: 3
Classifier: Programming Language :: Python :: 3.9
Classifier: Programming Language :: Python :: 3.10
Classifier: Programming Language :: Python :: 3.11
Classifier: Programming Language :: Python :: 3.12
Requires-Python: >=3.9
Requires-Dist: msapy>=1.7.3
Requires-Dist: myst-parser>=4.0.1
Requires-Dist: numba>=0.62.1
Requires-Dist: numpy>=2.3.4
Requires-Dist: requests>=2.32.5
Requires-Dist: scikit-learn>=1.7.2
Requires-Dist: scipy>=1.16.3
Requires-Dist: typeguard>=2.13.3
Provides-Extra: dev
Requires-Dist: pytest>=8.4.2; extra == 'dev'
Requires-Dist: sphinx-rtd-theme>=3.0.2; extra == 'dev'
Requires-Dist: sphinx>=8.2.3; extra == 'dev'
